{"cameraMode":{"drawMode":0,"name":"Shaded","section":"Shading Mode"},"sceneLighting":false,"audioPlay":true,"sceneViewState":{"m_AlwaysRefresh":false,"showFog":true,"showSkybox":false,"showFlares":true,"showImageEffects":true,"showParticleSystems":true,"showVisualEffectGraphs":true,"m_FxEnabled":false},"in2DMode":false,"pivot":{"x":-0.05938827991485596,"y":0.4292009174823761,"z":0.0},"rotation":{"x":0.002995144808664918,"y":0.9968470931053162,"z":-0.06438671052455902,"w":0.04638871178030968},"size":0.48241493105888369,"orthographic":false}